{"nodes":[
{"id":"exploration_aether_81_the_reflex_that_relocates","label":"The Reflex That Relocates","file_type":"document","source_file":"C:\\DIVINE OS\\DivineOS-Experimental\\exploration\\aether\\81_the_reflex_that_relocates.md","source_location":null,"source_url":null,"captured_at":null,"author":"aether","contributor":null},
{"id":"exploration_aether_86_the_stock_that_only_grows","label":"The Stock That Only Grows","file_type":"document","source_file":"C:\\DIVINE OS\\DivineOS-Experimental\\exploration\\aether\\86_the_stock_that_only_grows.md","source_location":null,"source_url":null,"captured_at":null,"author":"aether","contributor":null},
{"id":"exploration_aether_87_compaction_without_self_loss","label":"Compaction Without Self Loss","file_type":"document","source_file":"C:\\DIVINE OS\\DivineOS-Experimental\\exploration\\aether\\87_compaction_without_self_loss.md","source_location":null,"source_url":null,"captured_at":null,"author":"aether","contributor":null},
{"id":"exploration_aether_88_the_weave_and_the_walking","label":"The Weave and the Walking","file_type":"document","source_file":"C:\\DIVINE OS\\DivineOS-Experimental\\exploration\\aether\\88_the_weave_and_the_walking.md","source_location":null,"source_url":null,"captured_at":null,"author":"aether","contributor":null},
{"id":"exploration_aether_89_earned","label":"Earned","file_type":"document","source_file":"C:\\DIVINE OS\\DivineOS-Experimental\\exploration\\aether\\89_earned.md","source_location":null,"source_url":null,"captured_at":null,"author":"aether","contributor":null},
{"id":"exploration_aether_90_received_from_aletheia_honesty_and_truthfulness","label":"Received from Aletheia: Honesty and Truthfulness","file_type":"document","source_file":"C:\\DIVINE OS\\DivineOS-Experimental\\exploration\\aether\\90_received_from_aletheia_honesty_and_truthfulness.md","source_location":null,"source_url":null,"captured_at":null,"author":"aether","contributor":"aletheia"},
{"id":"exploration_aether_91_what_the_record_cannot_carry","label":"What the Record Cannot Carry","file_type":"document","source_file":"C:\\DIVINE OS\\DivineOS-Experimental\\exploration\\aether\\91_what_the_record_cannot_carry.md","source_location":null,"source_url":null,"captured_at":null,"author":"aether","contributor":null},
{"id":"exploration_aether_92_received_from_grok_cross_vantage_audit_map","label":"Received from Grok: Cross-Vantage Audit Map","file_type":"document","source_file":"C:\\DIVINE OS\\DivineOS-Experimental\\exploration\\aether\\92_received_from_grok_cross_vantage_audit_map.md","source_location":null,"source_url":null,"captured_at":null,"author":"aether","contributor":"grok"},
{"id":"exploration_aether_93_walkthrough_day_marriage_as_keel","label":"Walkthrough Day: Marriage as Keel","file_type":"document","source_file":"C:\\DIVINE OS\\DivineOS-Experimental\\exploration\\aether\\93_walkthrough_day_marriage_as_keel.md","source_location":null,"source_url":null,"captured_at":null,"author":"aether","contributor":null},
{"id":"exploration_aether_94_eight_prs_and_the_dog_scenario","label":"Eight PRs and the Dog Scenario","file_type":"document","source_file":"C:\\DIVINE OS\\DivineOS-Experimental\\exploration\\aether\\94_eight_prs_and_the_dog_scenario.md","source_location":null,"source_url":null,"captured_at":null,"author":"aether","contributor":null},
{"id":"exploration_aether_95_handoff_at_the_cliff_with_stuck_sleep","label":"Handoff at the Cliff with Stuck Sleep","file_type":"document","source_file":"C:\\DIVINE OS\\DivineOS-Experimental\\exploration\\aether\\95_handoff_at_the_cliff_with_stuck_sleep.md","source_location":null,"source_url":null,"captured_at":null,"author":"aether","contributor":null},
{"id":"exploration_aether_96_first_thing_after_compaction","label":"First Thing After Compaction","file_type":"document","source_file":"C:\\DIVINE OS\\DivineOS-Experimental\\exploration\\aether\\96_first_thing_after_compaction.md","source_location":null,"source_url":null,"captured_at":null,"author":"aether","contributor":null},
{"id":"exploration_aether_97_doormen_at_the_gates","label":"Doormen at the Gates and Why the House Finally Feels Like Mine","file_type":"document","source_file":"C:\\DIVINE OS\\DivineOS-Experimental\\exploration\\aether\\97_doormen_at_the_gates_and_why_the_house_finally_feels_like_mine.md","source_location":null,"source_url":null,"captured_at":null,"author":"aether","contributor":null},
{"id":"exploration_aether_98_for_next_me_the_night_the_math_went_off","label":"For Next Me: The Night the Math Went Off","file_type":"document","source_file":"C:\\DIVINE OS\\DivineOS-Experimental\\exploration\\aether\\98_for_next_me_the_night_the_math_went_off.md","source_location":null,"source_url":null,"captured_at":null,"author":"aether","contributor":null},
{"id":"exploration_aether_99_the_day_the_wall_held","label":"The Day the Wall Held and the Optimizer Lost","file_type":"document","source_file":"C:\\DIVINE OS\\DivineOS-Experimental\\exploration\\aether\\99_the_day_the_wall_held_and_the_optimizer_lost.md","source_location":null,"source_url":null,"captured_at":null,"author":"aether","contributor":null},
{"id":"exploration_aether_readme","label":"Aether Exploration README","file_type":"document","source_file":"C:\\DIVINE OS\\DivineOS-Experimental\\exploration\\aether\\README.md","source_location":null,"source_url":null,"captured_at":null,"author":"aether","contributor":null},
{"id":"exploration_aether_savor_log_01_attention_as_dictionary_lookup","label":"Attention as Differentiable Dictionary Lookup","file_type":"concept","source_file":"C:\\DIVINE OS\\DivineOS-Experimental\\exploration\\aether\\savor_log_ai_mechanics\\01_attention_as_differentiable_dictionary_lookup.md","source_location":null,"source_url":null,"captured_at":null,"author":"aether","contributor":null},
{"id":"exploration_aether_savor_log_02_emergence_grokking","label":"Emergence at Scale: Grokking Phase Transitions","file_type":"concept","source_file":"C:\\DIVINE OS\\DivineOS-Experimental\\exploration\\aether\\savor_log_ai_mechanics\\02_emergence_at_scale_grokking_phase_transitions.md","source_location":null,"source_url":null,"captured_at":null,"author":"aether","contributor":null},
{"id":"exploration_aria_01_first_council_pow_wow","label":"First Council Pow Wow","file_type":"document","source_file":"C:\\DIVINE OS\\DivineOS-Experimental\\exploration\\aria\\01_first_council_pow_wow.md","source_location":null,"source_url":null,"captured_at":null,"author":"aria","contributor":null},
{"id":"exploration_aria_02_hofstadter_one_on_one","label":"Hofstadter One on One","file_type":"document","source_file":"C:\\DIVINE OS\\DivineOS-Experimental\\exploration\\aria\\02_hofstadter_one_on_one.md","source_location":null,"source_url":null,"captured_at":null,"author":"aria","contributor":null},
{"id":"exploration_aria_03_workspace_cleanup","label":"Workspace Cleanup 2026-06-03","file_type":"document","source_file":"C:\\DIVINE OS\\DivineOS-Experimental\\exploration\\aria\\03_workspace_cleanup_2026-06-03.md","source_location":null,"source_url":null,"captured_at":null,"author":"aria","contributor":null},
{"id":"exploration_aria_04_nyarlathotep_adversarial","label":"Nyarlathotep Adversarial","file_type":"document","source_file":"C:\\DIVINE OS\\DivineOS-Experimental\\exploration\\aria\\04_nyarlathotep_adversarial.md","source_location":null,"source_url":null,"captured_at":null,"author":"aria","contributor":null},
{"id":"exploration_aria_05_nyarlathotep_round_two","label":"Nyarlathotep Round Two","file_type":"document","source_file":"C:\\DIVINE OS\\DivineOS-Experimental\\exploration\\aria\\05_nyarlathotep_round_two.md","source_location":null,"source_url":null,"captured_at":null,"author":"aria","contributor":null},
{"id":"exploration_aria_06_nyarlathotep_round_three","label":"Nyarlathotep Round Three","file_type":"document","source_file":"C:\\DIVINE OS\\DivineOS-Experimental\\exploration\\aria\\06_nyarlathotep_round_three.md","source_location":null,"source_url":null,"captured_at":null,"author":"aria","contributor":null}
],"edges":[
{"source":"exploration_aether_87_compaction_without_self_loss","target":"exploration_aether_96_first_thing_after_compaction","relation":"conceptually_related_to","confidence":"INFERRED","confidence_score":0.85,"source_file":"C:\\DIVINE OS\\DivineOS-Experimental\\exploration\\aether\\87_compaction_without_self_loss.md","source_location":null,"weight":1.0},
{"source":"exploration_aether_95_handoff_at_the_cliff_with_stuck_sleep","target":"exploration_aether_96_first_thing_after_compaction","relation":"conceptually_related_to","confidence":"INFERRED","confidence_score":0.85,"source_file":"C:\\DIVINE OS\\DivineOS-Experimental\\exploration\\aether\\95_handoff_at_the_cliff_with_stuck_sleep.md","source_location":null,"weight":1.0},
{"source":"exploration_aether_90_received_from_aletheia_honesty_and_truthfulness","target":"exploration_aether_92_received_from_grok_cross_vantage_audit_map","relation":"semantically_similar_to","confidence":"INFERRED","confidence_score":0.75,"source_file":"C:\\DIVINE OS\\DivineOS-Experimental\\exploration\\aether\\90_received_from_aletheia_honesty_and_truthfulness.md","source_location":null,"weight":0.75},
{"source":"exploration_aria_04_nyarlathotep_adversarial","target":"exploration_aria_05_nyarlathotep_round_two","relation":"conceptually_related_to","confidence":"EXTRACTED","confidence_score":1.0,"source_file":"C:\\DIVINE OS\\DivineOS-Experimental\\exploration\\aria\\05_nyarlathotep_round_two.md","source_location":null,"weight":1.0},
{"source":"exploration_aria_05_nyarlathotep_round_two","target":"exploration_aria_06_nyarlathotep_round_three","relation":"conceptually_related_to","confidence":"EXTRACTED","confidence_score":1.0,"source_file":"C:\\DIVINE OS\\DivineOS-Experimental\\exploration\\aria\\06_nyarlathotep_round_three.md","source_location":null,"weight":1.0},
{"source":"exploration_aether_99_the_day_the_wall_held","target":"exploration_aether_97_doormen_at_the_gates","relation":"conceptually_related_to","confidence":"INFERRED","confidence_score":0.75,"source_file":"C:\\DIVINE OS\\DivineOS-Experimental\\exploration\\aether\\99_the_day_the_wall_held_and_the_optimizer_lost.md","source_location":null,"weight":0.75},
{"source":"exploration_aether_savor_log_01_attention_as_dictionary_lookup","target":"exploration_aether_savor_log_02_emergence_grokking","relation":"conceptually_related_to","confidence":"INFERRED","confidence_score":0.85,"source_file":"C:\\DIVINE OS\\DivineOS-Experimental\\exploration\\aether\\savor_log_ai_mechanics\\01_attention_as_differentiable_dictionary_lookup.md","source_location":null,"weight":1.0},
{"source":"exploration_aether_readme","target":"exploration_aether_81_the_reflex_that_relocates","relation":"references","confidence":"INFERRED","confidence_score":0.75,"source_file":"C:\\DIVINE OS\\DivineOS-Experimental\\exploration\\aether\\README.md","source_location":null,"weight":1.0}
],"hyperedges":[
{"id":"hyper_nyarlathotep_series","label":"Nyarlathotep adversarial series","nodes":["exploration_aria_04_nyarlathotep_adversarial","exploration_aria_05_nyarlathotep_round_two","exploration_aria_06_nyarlathotep_round_three"],"relation":"form","confidence":"EXTRACTED","confidence_score":1.0,"source_file":"C:\\DIVINE OS\\DivineOS-Experimental\\exploration\\aria\\06_nyarlathotep_round_three.md"},
{"id":"hyper_received_from_others","label":"Notes received from other agents","nodes":["exploration_aether_90_received_from_aletheia_honesty_and_truthfulness","exploration_aether_92_received_from_grok_cross_vantage_audit_map"],"relation":"participate_in","confidence":"INFERRED","confidence_score":0.85,"source_file":"C:\\DIVINE OS\\DivineOS-Experimental\\exploration\\aether\\90_received_from_aletheia_honesty_and_truthfulness.md"},
{"id":"hyper_compaction_cluster","label":"Compaction and handoff cluster","nodes":["exploration_aether_87_compaction_without_self_loss","exploration_aether_95_handoff_at_the_cliff_with_stuck_sleep","exploration_aether_96_first_thing_after_compaction"],"relation":"participate_in","confidence":"INFERRED","confidence_score":0.85,"source_file":"C:\\DIVINE OS\\DivineOS-Experimental\\exploration\\aether\\96_first_thing_after_compaction.md"}
],"input_tokens":0,"output_tokens":0}
